columbo/__init__.py
columbo/_cli.py
columbo/_exception.py
columbo/_interaction.py
columbo/_types.py
columbo/_user_io.py
columbo/py.typed
columbo-0.14.0.dist-info/METADATA
columbo-0.14.0.dist-info/WHEEL
columbo-0.14.0.dist-info/licenses/LICENSE
columbo-0.14.0.dist-info/RECORD
