Metadata-Version: 2.1
Name: columbo
Version: 0.14.0
Summary: Specify a dynamic set of questions to ask a user and get their answers.
Project-URL: Homepage, https://github.com/plannigan/columbo
Project-URL: changelog, https://github.com/plannigan/columbo/blob/main/CHANGELOG.md
Project-URL: issues, https://github.com/plannigan/columbo/issues
Project-URL: documentation, https://plannigan.github.io/columbo
Author-email: Patrick Lannigan <p.lannigan@gmail.com>
License: MIT
License-File: LICENSE
Classifier: Development Status :: 4 - Beta
Classifier: License :: OSI Approved :: MIT License
Classifier: Programming Language :: Python
Classifier: Programming Language :: Python :: 3
Classifier: Programming Language :: Python :: 3.8
Classifier: Programming Language :: Python :: 3.9
Classifier: Programming Language :: Python :: 3.10
Classifier: Programming Language :: Python :: 3.11
Classifier: Programming Language :: Python :: 3.12
Requires-Python: >=3.8
Requires-Dist: prompt-toolkit~=3.0
Requires-Dist: typing-extensions<5,>=4.4.0; python_version < '3.10'
